{
  "probationPractitioners": [
    {
      "name": "Donald Turnip",
      "id": 5,
      "grade": "PO",
      "currentPercentage": 89,
      "remainingPoints": 312,
      "noOfCases": 18,
      "lastAllocated": "11/10/20"
    },
    {
      "name": "Pauline Hollywell",
      "id": 4,
      "grade": "PO",
      "currentPercentage": 105,
      "remainingPoints": 139,
      "noOfCases": 28,
      "lastAllocated": "01/10/20"
    },
    {
      "name": "Barry Cabana",
      "id": 3,
      "grade": "PO",
      "currentPercentage": 95,
      "remainingPoints": 156,
      "noOfCases": 25,
      "lastAllocated": "31/10/20"
    },
    {
      "name": "Maria Bury",
      "id": 2,
      "grade": "PO",
      "currentPercentage": 110,
      "remainingPoints": 98,
      "noOfCases": 32,
      "lastAllocated": "28/10/20"
    },
    {
      "name": "Camilla Horace",
      "id": 1,
      "grade": "PO",
      "currentPercentage": 95,
      "remainingPoints": 156,
      "noOfCases": 20,
      "lastAllocated": "28/10/20"
    }
  ],
  "serviceUsers": [ 
    { 
      "crn": "J678911",
      "pnc": "2012/123100000F",
      "name": "Sammy Toshack",
      "postcode": "SN5 12T",
      "age": 52,
      "gender": "male",
      "currentOM": 1,
      "allocationDate": "30/10/20",
      "previousCurrentOM":"",
      "risks": "Medium", 
      "sentence": "",
      "requirements": "",
      "rsrScore": 7.2,
      "OGRScoreOSPScore":"",
      "mappaOffender": "N",
      "publicInterestDefinition": "N",
      "foreignNational": "N",
      "highRosh": "Y",
      "deferredSentence": "N",
      "probabtionStatus": "Previously known",
      "offence": "Assault",
      "tier": "C2",
      "receivingFrom": "Community",
      "daysSinceSentence": "2",
      "sentenceStart": "30/10/20",
      "sentenceEnd": "28/11/2021"
    },
    { 
      "crn": "J678912",
      "pnc": "2012/123200000F",
      "name": "Stuart Perkins",
      "postcode": "SN4 6TT",
      "age": 26,
      "gender": "male",
      "currentOM": 2,
      "allocationDate": "31/10/20",
      "previousCurrentOM":"",
      "risks": "Low", 
      "sentence": "",
      "requirements": "",
      "rsrScore": 7.2,
      "OGRScoreOSPScore":"",
      "mappaOffender": "N",
      "publicInterestDefinition": "N",
      "foreignNational": "N",
      "highRosh": "Y",
      "deferredSentence": "N",
      "probabtionStatus": "No Record",
      "offence": "Armed Robbery",
      "tier": "B2",
      "receivingFrom": "Resettlement",
      "daysSinceSentence": "1",
      "sentenceStart": "31/10/20",
      "sentenceEnd": "30/7/2021"
    },
    { 
      "crn": "J678913",
      "pnc": "2012/123300000F",
      "name": "enola Fielding",
      "postcode": "SE3 23R",
      "age": 72,
      "gender": "female",
      "currentOM": 3,
      "allocationDate": "29/10/20",
      "previousCurrentOM":"",
      "risks": "High", 
      "sentence": "",
      "requirements": "",
      "rsrScore": 7.0,
      "OGRScoreOSPScore":"",
      "mappaOffender": "N",
      "publicInterestDefinition": "N",
      "foreignNational": "N",
      "highRosh": "Y",
      "deferredSentence": "N",
      "probabtionStatus": "No Record",
      "offence": "Sex offence",
      "tier": "B2",
      "receivingFrom": "Community",
      "daysSinceSentence": "3",
      "sentenceStart": "29/10/20",
      "sentenceEnd": "30/11/2021"
    },
    { 
      "crn": "J678914",
      "pnc": "2012/123400000F",
      "name": "Melinda Goodich",
      "postcode": "NE1 45S",
      "age": 34,
      "gender": "female",
      "currentOM": 4,
      "allocationDate": "30/10/20",
      "previousCurrentOM":"",
      "risks": "Low", 
      "sentence": "",
      "requirements": "",
      "rsrScore": 8.6,
      "OGRScoreOSPScore":"",
      "mappaOffender": "N",
      "publicInterestDefinition": "N",
      "foreignNational": "Y",
      "highRosh": "Y",
      "deferredSentence": "N",
      "probabtionStatus": "Current",
      "offence": "Assault",
      "tier": "C2",
      "receivingFrom": "Community",
      "daysSinceSentence": "2",
      "sentenceStart": "30/10/20",
      "sentenceEnd": "15/06/2021"
    },
    { 
      "crn": "J678915",
      "pnc": "2012/123500000F",
      "name": "Geoff Grazer",
      "postcode": "SN5 12T",
      "age": 52,
      "gender": "male",
      "currentOM": "",
      "allocationDate": "",
      "previousCurrentOM":"",
      "risks": "Medium", 
      "sentence": "",
      "requirements": "",
      "rsrScore": 7.2,
      "OGRScoreOSPScore":"",
      "mappaOffender": "N",
      "publicInterestDefinition": "N",
      "foreignNational": "N",
      "highRosh": "Y",
      "deferredSentence": "N",
      "probabtionStatus": "Previously known",
      "offence": "Assault",
      "tier": "C2",
      "receivingFrom": "Community",
      "daysSinceSentence": "2",
      "sentenceStart": "30/10/20",
      "sentenceEnd": "28/11/2021"
    },
    { 
      "crn": "J678916",
      "pnc": "2012/123600000F",
      "name": "Marco Botton",
      "postcode": "SN4 6TT",
      "age": 26,
      "gender": "male",
      "currentOM": "",
      "allocationDate": "",
      "previousCurrentOM":"",
      "risks": "Low", 
      "sentence": "",
      "requirements": "",
      "rsrScore": 7.2,
      "OGRScoreOSPScore":"",
      "mappaOffender": "N",
      "publicInterestDefinition": "N",
      "foreignNational": "N",
      "highRosh": "Y",
      "deferredSentence": "N",
      "probabtionStatus": "No Record",
      "offence": "Armed Robbery",
      "tier": "B2",
      "receivingFrom": "Resettlement",
      "daysSinceSentence": "1",
      "sentenceStart": "31/10/20",
      "sentenceEnd": "30/7/2021"
    },
    { 
      "crn": "J678917",
      "pnc": "2012/123700000F",
      "name": "Maria Maclachlan",
      "postcode": "SE3 23R",
      "age": 72,
      "gender": "female",
      "currentOM": "",
      "allocationDate": "",
      "previousCurrentOM":"",
      "risks": "High", 
      "sentence": "",
      "requirements": "",
      "rsrScore": 7.0,
      "OGRScoreOSPScore":"",
      "mappaOffender": "N",
      "publicInterestDefinition": "N",
      "foreignNational": "N",
      "highRosh": "Y",
      "deferredSentence": "N",
      "probabtionStatus": "No Record",
      "offence": "Sex offence",
      "tier": "B2",
      "receivingFrom": "Community",
      "daysSinceSentence": "3",
      "sentenceStart": "29/10/20",
      "sentenceEnd": "30/11/2021"
    },
    { 
      "crn": "J6789108",
      "pnc": "2012/123800000F",
      "name": "Valerie Liberty",
      "postcode": "NE1 45S",
      "age": 34,
      "gender": "female",
      "currentOM": "",
      "allocationDate": "",
      "previousCurrentOM":"",
      "risks": "Low", 
      "sentence": "",
      "requirements": "",
      "rsrScore": 8.6,
      "OGRScoreOSPScore":"",
      "mappaOffender": "N",
      "publicInterestDefinition": "N",
      "foreignNational": "Y",
      "highRosh": "Y",
      "deferredSentence": "N",
      "probabtionStatus": "Current",
      "offence": "Assault",
      "tier": "C2",
      "receivingFrom": "Community",
      "daysSinceSentence": "2",
      "sentenceStart": "30/10/20",
      "sentenceEnd": "15/06/2021"
    }
  ]
}
